autogencap/Actor.py
autogencap/ActorConnector.py
autogencap/Broker.py
autogencap/ComponentEnsemble.py
autogencap/Config.py
autogencap/Constants.py
autogencap/DebugLog.py
autogencap/DirectorySvc.py
autogencap/__init__.py
autogencap/requirements.txt
autogencap/setup.py
autogencap/utility.py
autogencap/ag_adapter/AG2CAP.py
autogencap/ag_adapter/AGActor.py
autogencap/ag_adapter/AutoGenConnector.py
autogencap/ag_adapter/CAP2AG.py
autogencap/ag_adapter/CAPGroupChat.py
autogencap/ag_adapter/CAPGroupChatManager.py
autogencap/ag_adapter/CAPPair.py
autogencap/ag_adapter/__init__.py
autogencap/ag_adapter/agent.py
autogencap/proto/Autogen.proto
autogencap/proto/Autogen_pb2.py
autogencap/proto/Autogen_pb2.pyi
autogencap/proto/CAP.proto
autogencap/proto/CAP_pb2.py
autogencap/proto/CAP_pb2.pyi
autogencap/proto/__init__.py
autogencap/proto/proto-instructions.txt
autogencap/proto/protoc.exe
autogencap/proto/test.seqdiag
autogencap-0.0.11.dist-info/METADATA
autogencap-0.0.11.dist-info/WHEEL
autogencap-0.0.11.dist-info/RECORD
